image_rotator/__init__.py
image_rotator/rotate.py
image_rotator-0.1.0.dist-info/licenses/LICENSE
image_rotator-0.1.0.dist-info/METADATA
image_rotator-0.1.0.dist-info/WHEEL
image_rotator-0.1.0.dist-info/top_level.txt
image_rotator-0.1.0.dist-info/RECORD
